gitlab_jira_integration/__init__.py
gitlab_jira_integration/config_manager.py
gitlab_jira_integration/gitlab_client.py
gitlab_jira_integration/jira_client.py
gitlab_jira_integration/main.py
gitlab_jira_integration/test_mode.py
gitlab_jira_integration/version_manager.py
gitlab_jira_integration-0.2.3.dist-info/licenses/LICENSE
gitlab_jira_integration-0.2.3.dist-info/METADATA
gitlab_jira_integration-0.2.3.dist-info/WHEEL
gitlab_jira_integration-0.2.3.dist-info/entry_points.txt
gitlab_jira_integration-0.2.3.dist-info/top_level.txt
gitlab_jira_integration-0.2.3.dist-info/RECORD
