Metadata-Version: 2.4
Name: gitlab-jira-integration
Version: 0.2.3
Summary: GitLab Jira Integration
Author-email: Alair Junior <alairjt@gmail.com>
Project-URL: Homepage, https://github.com/alairjt/gitlab-jira-integration
Project-URL: BugTracker, https://github.com/alairjt/gitlab-jira-integration/issues
Classifier: Programming Language :: Python :: 3
Classifier: License :: OSI Approved :: MIT License
Classifier: Operating System :: OS Independent
Requires-Python: >=3.7
License-File: LICENSE
Requires-Dist: python-gitlab
Requires-Dist: jira
Requires-Dist: semver
Requires-Dist: pyyaml
Provides-Extra: test
Requires-Dist: pytest; extra == "test"
Requires-Dist: pytest-mock; extra == "test"
Requires-Dist: responses; extra == "test"
Dynamic: license-file
